gfetchert/__init__.py
gfetchert/core.py
gfetchert/file_ops.py
gfetchert/geocode.py
gfetchert-0.1.8.dist-info/licenses/LICENSE
gfetchert-0.1.8.dist-info/METADATA
gfetchert-0.1.8.dist-info/WHEEL
gfetchert-0.1.8.dist-info/top_level.txt
gfetchert-0.1.8.dist-info/RECORD
