Metadata-Version: 2.4
Name: gfetchert
Version: 0.1.8
Summary: Fetch CHIRPS rainfall data easily for any date and location using latitude/longitude or place name.
Author-email: Crocodile <nikhilcy107@gmail.com>
License: MIT
Project-URL: Homepage, https://github.com/1nikhilff/GfetcherT
Project-URL: Dataset, https://www.chc.ucsb.edu/data/chirps
Requires-Python: >=3.9
License-File: LICENSE
Requires-Dist: pandas
Requires-Dist: rasterio
Requires-Dist: requests
Requires-Dist: geopy
Requires-Dist: tqdm
Dynamic: license-file
